{"@context": "http://schema.org", "@type": "JobPosting", "baseSalary": {"@type": "MonetaryAmount", "currency": "GBP", "value": {"@type": "QuantitativeValue", "maxValue": "30615", "minValue": "24907", "unitText": "YEAR", "value": "\u00a324,907 - \u00a330,615 Per annum pro rata"}}, "datePosted": "2020-10-30T10:46:25+0000", "description": "&lt;p&gt;An exciting opportunity has arisen for Band 5 staff nurses on ward 111, a fast paced, refurbished unit specialising in Plastics, Max Fax, Breast surgery and ENT including Tracheostomy and Laryngectomy care offering a wealth of learning opportunities. However, we also care for patients with other varying surgical conditions.&lt;/p&gt;\n&lt;p&gt;&lt;br /&gt;The ward can offer a full induction package with a supernumerary period. Training and competencies within the specialities and on-going support and professional development. In line with service development ward 111 works within the 12 hour shift pattern but can offer flexibility of any applicant that feels the 12 hour is not suitable.&lt;/p&gt;\n&lt;p&gt;&lt;br /&gt;The ideal candidate will have enthusiasm to work within a motivated team to provide high quality care through evidence based practice and innovation. The candidate is preferred to have surgical experience and basic computer skills along with excellent communication skills; experience in tracheostomy care is also desirable but not essential. They will work under the guidance of the Senior Sister and mentor.&lt;/p&gt;\n&lt;p&gt;&lt;br /&gt;For further comprehensive role details please see the job description and person specification attached.&lt;/p&gt;\n&lt;p&gt;For any information please get in touch with Mandy Somerset 01782 676111 or by email Amanda.somerset@uhnm.nhs.uk&lt;/p&gt;\n&lt;p&gt;\u00a0&lt;/p&gt;\n&lt;p&gt;For further details / informal visits contact:&lt;/p&gt;\n&lt;p&gt;Nameamanda somersetJob titlessrEmail addressamanda.somerset@uhnm.nhs.ukTelephone number01782 676111&lt;/p&gt;", "employmentType": "FULL_TIME", "hiringOrganization": {"@type": "Organization", "name": "University Hospitals of North Midlands NHS Trust", "url": "https://www.jobs.nhs.uk/xi/agency_info/?agency_id=122653"}, "industry": "Healthcare", "jobLocation": {"@type": "Place", "address": {"@type": "PostalAddress", "addressCountry": "GB", "addressLocality": "Royal Stoke, stoke on trent", "postalCode": "ST4 6QG"}, "geo": {"@type": "GeoCoordinates", "latitude": "53.004", "longitude": "-2.21487"}}, "title": "Staff Nurse", "url": "https://www.jobs.nhs.uk/xi/vacancy/916249781", "validThrough": "2020-11-08T23:59:59+0000"}