{"@context": "http://schema.org", "@type": "JobPosting", "baseSalary": {"@type": "MonetaryAmount", "currency": "GBP", "value": {"@type": "QuantitativeValue", "unitText": "YEAR", "value": "ACC Qualified"}}, "datePosted": "2020-10-21T11:46:08+0100", "description": "&lt;p&gt;&lt;strong&gt;Accredited Clinical Coder Band 4 with 15% Recruitment &amp; Retention Premium&lt;/strong&gt;&lt;/p&gt;\n&lt;p&gt;PLEASE NOTE WE ARE ONLY ACCEPTING APPLICATIONS FROM ACC CLINICAL CODERS&lt;/p&gt;\n&lt;p&gt;Here at Sandwell and West Birmingham Hospitals NHS Trust we believe that everyone matters.&lt;/p&gt;\n&lt;p&gt;We are looking for an Accredited Clinical Coder who is self-motivated and enthusiastic with excellent communication skills to join our team.&lt;/p&gt;\n&lt;p&gt;You will need to have significant coding experience and sound knowledge in the use of patient information and coding systems used within the NHS and can deliver a high standard of coding completeness and accuracy in a timely manner to meet commissioning and Payment by Results timescales. In return we offer ongoing training and development supporting all of our staff to develop professionally and personally.&lt;/p&gt;\n&lt;p&gt;You will need to;&lt;/p&gt;\n&lt;ul&gt;\n&lt;li&gt;Have experience of clinical coding a wide range of specialties.&lt;/li&gt;\n&lt;li&gt;Demonstrate a high level of accuracy, adhering to national standards and conventions.&lt;/li&gt;\n&lt;li&gt;Flexible in your approach you must be able to work as part of a team to tight deadlines.&lt;/li&gt;\n&lt;li&gt;Exhibit excellent analytical skills with a good knowledge of medical terminology, anatomy and physiology&lt;/li&gt;\n&lt;/ul&gt;\n&lt;p&gt;For further details / informal visits contact:&lt;/p&gt;\n&lt;p&gt;Name: Sally Nicholds&lt;br /&gt;Job title: Clinical Coding Manager&lt;br /&gt;Email address: Sally.Nicholds@nhs.net&lt;br /&gt;Telephone number: 0121 507 6161&lt;br /&gt;&lt;br /&gt;Additional contact information&lt;/p&gt;\n&lt;p&gt;Matthew Maguire, telephone 07971155721, email matthew.maguire@nhs.net&lt;/p&gt;", "employmentType": "FULL_TIME", "hiringOrganization": {"@type": "Organization", "logo": "https://www.jobs.nhs.uk/xi/db_image/logo/120738.gif", "name": "Sandwell and West Birmingham Hospitals NHS Trust", "url": "https://www.jobs.nhs.uk/xi/agency_info/?agency_id=120738"}, "industry": "Healthcare", "jobLocation": {"@type": "Place", "address": {"@type": "PostalAddress", "addressCountry": "GB", "addressLocality": "Sandwell, West Bromwich", "postalCode": "B71 4HJ"}, "geo": {"@type": "GeoCoordinates", "latitude": "52.5274", "longitude": "-1.98788"}}, "title": "Senior Clinical Coder", "url": "https://www.jobs.nhs.uk/xi/vacancy/916236173", "validThrough": "2020-11-20T23:59:59+0000"}