{"@context": "http://schema.org", "@type": "JobPosting", "baseSalary": {"@type": "MonetaryAmount", "currency": "GBP", "value": {"@type": "QuantitativeValue", "maxValue": "44503", "minValue": "38890", "unitText": "YEAR", "value": "\u00a338,890 - \u00a344,503 per annum pro rata"}}, "datePosted": "2020-11-02T11:15:54+0000", "description": "&lt;p&gt;This post offers an exciting and challenging opportunity for staff members working at an advanced level of practice to join a committed team providing urgent care to patients living in North East Wales. The urgent care practitioner will be expected to provide a high level of clinical expertise, knowledge and skills in the treatment of patients accessing the GP Out of Hours setting. This will include taking the lead role in the clinical assessment, diagnosis, treatment and management of patients who may present with acute/urgent needs at time when their GP surgeries are closed. The practitioner will be expected to work closely with the multifaceted team as well as autonomously at times. The autonomous practitioner role is part of an Out of Hours team caring for the population of Conwy and Denbighshire during evenings, nights, weekends and Bank Holidays.&lt;/p&gt;\n&lt;p&gt;The ability to speak Welsh is desirable for this post; Welsh and/or English speakers are equally welcome to apply.\u00a0&lt;/p&gt;\n&lt;p&gt;Closing Date: 16/11/2020\u00a0&lt;/p&gt;\n&lt;p&gt;For further details / informal visits contact:&lt;/p&gt;\n&lt;p&gt;Sara Rathmill - Matron&lt;/p&gt;\n&lt;p&gt;Tel: 01745 534981&lt;/p&gt;\n&lt;p&gt;Email: sara.rathmill@wales.nhs.uk\u00a0&lt;/p&gt;", "employmentType": "FULL_TIME", "hiringOrganization": {"@type": "Organization", "logo": "https://www.jobs.nhs.uk/xi/db_image/logo/123196.JPG", "name": "Betsi Cadwaladr University Local Health Board", "url": "https://www.jobs.nhs.uk/xi/agency_info/?agency_id=123196"}, "industry": "Healthcare", "jobLocation": {"@type": "Place", "address": {"@type": "PostalAddress", "addressCountry": "GB", "addressLocality": "Ysbyty Glan Clwyd, Conwy and Denbighshire", "postalCode": "LL57 2PW"}, "geo": {"@type": "GeoCoordinates", "latitude": "53.209", "longitude": "-4.15983"}}, "title": "Urgent Care Practitioner", "url": "https://www.jobs.nhs.uk/xi/vacancy/916251743", "validThrough": "2020-11-16T23:59:59+0000"}